Metadata-Version: 2.1
Name: proton-db-api
Version: 0.1
Summary: Simple unofficial ProtonDB API for python
Home-page: https://github.com/vovsss/proton_db_api
Author: vovsss
Author-email: vova4ka@internet.ru
License: MIT
License-File: LICENSE
